{
    "build": {
        "content": [
            {
                "files": [
                    "app-themes/**.md",
                    "flex-layouts/**.md",
                    "generate-app/**.md",
                    "master-detail/**.md",
                    "guide-to-variables-in-app-builder/**.md",
                    "indigo-design-components/**.md",
                    "spa-and-navigation/**.md",
                    "using-data-in-your-app/**.md",
                    "ui-kits/**.md",
                    "ai/**.md",
                    "sdk/**.md",
                    "on-premises/**.md",
                    "toolbox/**.md",
                    "how-to/**.md",
                    "sidebar-toc/toc.yml",
                    "toc.yml",
                    "*.md"
                ],
                "exclude": ["obj/**", "_site/**"]
            }
        ],
        "resource": [
            {
                "files": ["images/**","web.config"],
                "exclude": ["obj/**", "_site/**"]
            }
        ],
        "overwrite": [
            {
                "files": ["apidoc/**.md"],
                "exclude": ["obj/**", "_site/**"]
            }
        ],
        "dest": "_site",
        "globalMetadataFiles": ["global.json", "../node_modules/igniteui-docfx-template/template/bundling.global.json"],
        "globalMetadata": {
            "_appFaviconPath": "https://staging.appbuilder.dev/wp-content/themes/slingshot/icons/favicon.ico"
        },
        "fileMetadataFiles": [],
        "template": ["../node_modules/igniteui-docfx-template/template"],
        "noLangKeyword": false,
        "keepFileLink": false,
        "cleanupCacheHistory": true,
        "disableGitFeatures": true,
        "sitemap": {
            "baseUrl": "https://www.appbuilder.dev/help/",
            "changefreq": "weekly",
            "priority": 0.7
        }
    }
}
